LICENSE
MANIFEST.in
README.rst
requirements.txt
setup.cfg
setup.py
versioneer.py
./.travis.yml
./environment.yml
./readthedocs.yml
./conda/meta.yaml
./docs/environment.yml
./docs/build/html/api.html
./docs/build/html/genindex.html
./docs/build/html/index.html
./docs/build/html/quickstart.html
./docs/build/html/search.html
./docs/build/html/_modules/index.html
./docs/build/html/_modules/intake_xarray.html
./docs/build/html/_modules/intake_xarray/netcdf.html
./docs/build/html/_modules/intake_xarray/xzarr.html
./tests/WFPC.fits
./tests/WFPC_copy.fits
intake_astro/__init__.py
intake_astro/_version.py
intake_astro/array.py
intake_astro/table.py
intake_astro.egg-info/PKG-INFO
intake_astro.egg-info/SOURCES.txt
intake_astro.egg-info/dependency_links.txt
intake_astro.egg-info/not-zip-safe
intake_astro.egg-info/pbr.json
intake_astro.egg-info/requires.txt
intake_astro.egg-info/top_level.txt
tests/__init__.py
tests/test_array.py
tests/test_dataframe.py