Metadata-Version: 1.2
Name: intake-astro
Version: 0.1.1
Summary: Astronomy plugins for Intake
Home-page: https://github.com/ContinuumIO/intake-astro
Maintainer: Martin Durant
Maintainer-email: mdurant@anaconda.com
License: BSD
Platform: UNKNOWN
